kaviar-1.0.dist-info/DESCRIPTION.rst
kaviar-1.0.dist-info/metadata.json
kaviar-1.0.dist-info/METADATA
kaviar-1.0.dist-info/WHEEL
kaviar-1.0.dist-info/RECORD
kaviar-1.0.dist-info/top_level.txt
kaviar/filters.py
kaviar/__init__.py
kaviar/escaping.py
kaviar/dumping.py
kaviar/filterbase.py
kaviar/functools.py
kaviar/adapter.py
kaviar/testableiter.py
kaviar/api.py
kaviar/auxiliary.py
